sqlcc.py
sqlccc-1.1.1.dist-info/licenses/LICENSE
sqlccc-1.1.1.dist-info/METADATA
sqlccc-1.1.1.dist-info/WHEEL
sqlccc-1.1.1.dist-info/top_level.txt
sqlccc-1.1.1.dist-info/RECORD
